multi_az_observability/__init__.py
multi_az_observability/py.typed
multi_az_observability/_jsii/__init__.py
multi_az_observability/_jsii/multi-az-observability@0.0.1-alpha.25.jsii.tgz
multi_az_observability-0.0.1a25.dist-info/LICENSE
multi_az_observability-0.0.1a25.dist-info/METADATA
multi_az_observability-0.0.1a25.dist-info/WHEEL
multi_az_observability-0.0.1a25.dist-info/top_level.txt
multi_az_observability-0.0.1a25.dist-info/RECORD
